ssp_gh/__init__.py
ssp_gh/cli.py
ssp_gh/settings.py
ssp_gh-0.0.1.dist-info/LICENSE
ssp_gh-0.0.1.dist-info/METADATA
ssp_gh-0.0.1.dist-info/WHEEL
ssp_gh-0.0.1.dist-info/entry_points.txt
ssp_gh-0.0.1.dist-info/top_level.txt
ssp_gh-0.0.1.dist-info/RECORD
