Metadata-Version: 2.1
Name: ssp-gh
Version: 0.0.1
Summary: GitHub demonstration for serious-scaffold-python.
Author-email: huxuan <i@huxuan.org>
Project-URL: homepage, https://github.com/huxuan/ssp-gh/
Project-URL: issue, https://github.com/huxuan/ssp-gh/issues
Keywords: development-focused,project template
Classifier: Development Status :: 3 - Alpha
Classifier: License :: OSI Approved :: MIT License
Classifier: Operating System :: OS Independent
Classifier: Programming Language :: Python :: 3.10
Classifier: Programming Language :: Python :: 3.11
Classifier: Programming Language :: Python :: 3.12
Classifier: Programming Language :: Python :: 3.8
Classifier: Programming Language :: Python :: 3.9
Requires-Python: >=3.8
License-File: LICENSE
Requires-Dist: pydantic-settings
Requires-Dist: typer[all]
Provides-Extra: docs
Requires-Dist: autodoc-pydantic ; extra == 'docs'
Requires-Dist: coverage ; extra == 'docs'
Requires-Dist: furo ; extra == 'docs'
Requires-Dist: git-changelog ; extra == 'docs'
Requires-Dist: mypy[reports] ; extra == 'docs'
Requires-Dist: myst-parser ; extra == 'docs'
Requires-Dist: pytest ; extra == 'docs'
Requires-Dist: Sphinx ; extra == 'docs'
Requires-Dist: sphinx-autobuild ; extra == 'docs'
Requires-Dist: sphinx-click ; extra == 'docs'
Requires-Dist: sphinx-togglebutton ; extra == 'docs'
Provides-Extra: lint
Requires-Dist: black ; extra == 'lint'
Requires-Dist: isort ; extra == 'lint'
Requires-Dist: mypy ; extra == 'lint'
Requires-Dist: ruff ; extra == 'lint'
Requires-Dist: toml-sort ; extra == 'lint'
Provides-Extra: package
Requires-Dist: build ; extra == 'package'
Requires-Dist: setuptools-scm ; extra == 'package'
Requires-Dist: twine ; extra == 'package'
Provides-Extra: test
Requires-Dist: coverage ; extra == 'test'
Requires-Dist: pytest ; extra == 'test'
